README.rst
setup.py
django_moova.egg-info/PKG-INFO
django_moova.egg-info/SOURCES.txt
django_moova.egg-info/dependency_links.txt
django_moova.egg-info/requires.txt
django_moova.egg-info/top_level.txt
moova/connector.py
moova/handler.py
moova/settings.py