Metadata-Version: 2.1
Name: django-moova
Version: 2.1.0
Summary: Django Moova Integration
Home-page: https://gitlab.com/linets/ecommerce/oms/integrations/oms-moova/
Author: Linets Development Team
Author-email: dteam@linets.cl
License: MIT
Platform: UNKNOWN
Requires-Python: >=3.7
